prometheus_summary/__init__.py
prometheus_summary/version.py
prometheus_summary-0.1.4.dist-info/LICENSE
prometheus_summary-0.1.4.dist-info/METADATA
prometheus_summary-0.1.4.dist-info/WHEEL
prometheus_summary-0.1.4.dist-info/top_level.txt
prometheus_summary-0.1.4.dist-info/RECORD
